{
    "buttonRectXYXY": [
      [
        0,
        0,
        0,
        0
      ],
      [
        0,
        0,
        0,
        0
      ],
      [
        0,
        0,
        0,
        0
      ]
    ],
    "buttonSize": 3,
    "moveRectXYXY": [
        0,
        0,
        0,
        0
    ],
    "picMaskName": "data/phonemaskU.bmp",
    "picName": "data/phoneU.bmp",
    "showDirection": 0,
    "showRectXYWH": [
        35,
        112,
        100,
        100
    ],
    "touchRectXYWH": [
        35,
        112,
        100,
        100
    ],
    "isEnable":0,
    "version": "1.0.0"
}